vikash/Debug.py
vikash/__init__.py
vikash-0.1.dist-info/LICENSE.text
vikash-0.1.dist-info/METADATA
vikash-0.1.dist-info/WHEEL
vikash-0.1.dist-info/top_level.txt
vikash-0.1.dist-info/RECORD
