Metadata-Version: 2.1
Name: vikash
Version: 0.1
Summary: <>
Author-email: Vikash Singh <vikashofficial000@gmail.com>
Classifier: Programming Language :: Python :: 3
Classifier: License :: OSI Approved :: MIT License
Classifier: Operating System :: OS Independent
Requires-Python: >=3.7
License-File: LICENSE.text
